[{"id":"defaultAction","val":"dummy","type":"normal","filter":"","is3rd":true},{"id":1504678825199,"val":"waylee.net","type":"block","filter":"","isregexp":false,"is3rd":true,"isfrom":false,"isto":true},{"id":1504679180429,"val":"isnowfy.com","type":"block","filter":"","isregexp":false,"is3rd":true,"isfrom":false,"isto":true},{"id":1504679272919,"val":"sinaimg.cn","type":"block","filter":"","isregexp":false,"is3rd":true,"isfrom":false,"isto":true},{"id":1504679312648,"val":"hiphotos.baidu.com","type":"block","filter":"","isregexp":false,"is3rd":true,"isfrom":false,"isto":true},{"id":1504769258705,"val":"qpic.cn","type":"block","filter":"","isregexp":false,"is3rd":true,"isfrom":false,"isto":true},{"id":1504770045152,"val":"qlogo.cn","type":"block","filter":"","isregexp":false,"is3rd":false,"isfrom":false,"isto":true},{"id":1504770056058,"val":"","type":"normal","filter":"","isregexp":false,"is3rd":false,"isfrom":true,"isto":true}]